invidious_parser/__init__.py
invidious_parser/baseapi.py
invidious_parser/builder.py
invidious_parser/channelapi.py
invidious_parser/connection_config.py
invidious_parser/invidious_api.py
invidious_parser/invidious_config.py
invidious_parser/invidious_instance.py
invidious_parser/invidious_parser.py
invidious_parser/playlistapi.py
invidious_parser/receiver.py
invidious_parser/videoapi.py
invidious_parser-1.3.3.dist-info/METADATA
invidious_parser-1.3.3.dist-info/WHEEL
invidious_parser-1.3.3.dist-info/top_level.txt
invidious_parser-1.3.3.dist-info/RECORD
