Metadata-Version: 2.1
Name: invidious-parser
Version: 1.3.3
Summary: Getting information via invidious api.
Author-email: Kostiantyn Klochko <kostya_klochko@ukr.net>
License: GNU GENERAL PUBLIC LICENSE
Project-URL: Homepage, https://gitlab.com/universe-tube/universe-tube-connect-modules/invidious-parser
Project-URL: Bug Tracker, https://gitlab.com/universe-tube/universe-tube-connect-modules/invidious-parser/issues
Classifier: Programming Language :: Python :: 3
Classifier: License :: OSI Approved :: GNU General Public License v3 or later (GPLv3+)
Classifier: Operating System :: OS Independent
Requires-Python: >=3.7
Requires-Dist: requests (~=2.28.2)
